loxpy/AstPrinter.py
loxpy/Environment.py
loxpy/ErrorState.py
loxpy/Expr.py
loxpy/Interpreter.py
loxpy/Lox.py
loxpy/LoxCallable.py
loxpy/LoxFunction.py
loxpy/LoxRuntimeError.py
loxpy/Parser.py
loxpy/ParserError.py
loxpy/Return.py
loxpy/Scanner.py
loxpy/ScannerError.py
loxpy/Stmt.py
loxpy/Tokens.py
loxpy/__init__.py
loxpy/__main__.py
loxpy-0.1.1.dist-info/LICENSE
loxpy-0.1.1.dist-info/METADATA
loxpy-0.1.1.dist-info/WHEEL
loxpy-0.1.1.dist-info/entry_points.txt
loxpy-0.1.1.dist-info/top_level.txt
loxpy-0.1.1.dist-info/RECORD
