Metadata-Version: 2.1
Name: loxpy
Version: 0.1.1
Summary: A small implemetation of lox with python
Home-page: https://github.com/largomst/LoxPy
Author: largomst
Author-email: yukater@outlook.com
License: UNKNOWN
Platform: UNKNOWN
Classifier: Programming Language :: Python :: 3
Classifier: License :: OSI Approved :: MIT License
Classifier: Operating System :: OS Independent
